megadex
