Metadata-Version: 1.0
Name: megadex
Version: 0.0.8
Summary: Mega Indexer
Home-page: https://github.com/hodgesds/megadex
Author: Daniel Hodges
Author-email: hodges.daniel.scott@gmail.com
License: UNKNOWN
Platform: UNKNOWN
